weightedpandas/__init__.py
weightedpandas/core.py
weightedpandas-0.1.0.dist-info/LICENSE
weightedpandas-0.1.0.dist-info/METADATA
weightedpandas-0.1.0.dist-info/WHEEL
weightedpandas-0.1.0.dist-info/top_level.txt
weightedpandas-0.1.0.dist-info/RECORD
