Metadata-Version: 2.2
Name: weightedpandas
Version: 0.1.0
Summary: Extends pandas Series and DataFrame classes to support weighted operations
Author: WeightedPandas Contributors
License: MIT
Project-URL: Homepage, https://github.com/policyengine/weightedpandas
Project-URL: Bug Tracker, https://github.com/policyengine/weightedpandas/issues
Project-URL: Documentation, https://github.com/policyengine/weightedpandas
Classifier: Development Status :: 3 - Alpha
Classifier: Intended Audience :: Developers
Classifier: Intended Audience :: Science/Research
Classifier: License :: OSI Approved :: MIT License
Classifier: Programming Language :: Python :: 3
Classifier: Programming Language :: Python :: 3.8
Classifier: Programming Language :: Python :: 3.9
Classifier: Programming Language :: Python :: 3.10
Classifier: Programming Language :: Python :: 3.11
Classifier: Topic :: Scientific/Engineering
Classifier: Topic :: Scientific/Engineering :: Information Analysis
Classifier: Operating System :: OS Independent
Requires-Python: >=3.8
License-File: LICENSE
Requires-Dist: pandas<3.0.0,>=1.4.0
Requires-Dist: numpy<3.0.0,>=1.20.0
Provides-Extra: dev
Requires-Dist: pytest>=7.0.0; extra == "dev"
Requires-Dist: pytest-cov>=4.0.0; extra == "dev"
Requires-Dist: black>=23.0.0; extra == "dev"
Requires-Dist: isort>=5.0.0; extra == "dev"
Requires-Dist: flake8>=6.0.0; extra == "dev"
Requires-Dist: mypy>=1.0.0; extra == "dev"
Provides-Extra: docs
Requires-Dist: jupyter-book>=0.13.0; extra == "docs"
Requires-Dist: sphinx>=4.0; extra == "docs"
Requires-Dist: sphinx_rtd_theme; extra == "docs"
Requires-Dist: sphinx-autodoc-typehints; extra == "docs"
Requires-Dist: sphinx_book_theme; extra == "docs"
Requires-Dist: furo; extra == "docs"
Requires-Dist: matplotlib; extra == "docs"
